singyeong/__init__.py
singyeong/backoff.py
singyeong/client.py
singyeong/dsn.py
singyeong/enums.py
singyeong/exceptions.py
singyeong/message.py
singyeong/query.py
singyeong/types.py
singyeong/utils.py
singyeong/websocket.py
singyeong.py-1.0.1.dist-info/LICENSE
singyeong.py-1.0.1.dist-info/METADATA
singyeong.py-1.0.1.dist-info/WHEEL
singyeong.py-1.0.1.dist-info/top_level.txt
singyeong.py-1.0.1.dist-info/RECORD
