Metadata-Version: 2.1
Name: singyeong.py
Version: 1.0.1
Summary: An asynchronous client for 신경.
Home-page: https://github.com/StartITBot/singyeong.py
Author: StartIT
License: MIT
Project-URL: StartIT Bot, https://startit.fun/
Project-URL: Issue tracker, https://github.com/StartITBot/singyeong.py/issues
Platform: any
Classifier: Development Status :: 2 - Pre-Alpha
Classifier: Framework :: AsyncIO
Classifier: Intended Audience :: Developers
Classifier: License :: OSI Approved :: MIT License
Classifier: Natural Language :: English
Classifier: Operating System :: OS Independent
Classifier: Programming Language :: Python :: 3 :: Only
Classifier: Programming Language :: Python :: 3.6
Classifier: Programming Language :: Python :: 3.7
Classifier: Programming Language :: Python :: 3.8
Classifier: Programming Language :: Python :: 3.9
Classifier: Programming Language :: Python :: Implementation :: CPython
Classifier: Topic :: Internet
Classifier: Topic :: Utilities
Classifier: Topic :: System :: Networking
Classifier: Topic :: Software Development :: Libraries
Requires-Python: >=3.6
Requires-Dist: setuptools (~=53.0.0)
Requires-Dist: websockets (~=8.1)
Provides-Extra: msgpack
Requires-Dist: msgpack ; extra == 'msgpack'
Provides-Extra: ujson
Requires-Dist: ujson ; extra == 'ujson'
